agenta/__init__.py
agenta/client/Readme.md
agenta/client/__init__.py
agenta/client/backend/__init__.py
agenta/client/backend/access_control/__init__.py
agenta/client/backend/access_control/client.py
agenta/client/backend/access_control/raw_client.py
agenta/client/backend/admin/__init__.py
agenta/client/backend/admin/client.py
agenta/client/backend/admin/raw_client.py
agenta/client/backend/annotations/__init__.py
agenta/client/backend/annotations/client.py
agenta/client/backend/annotations/raw_client.py
agenta/client/backend/api_keys/__init__.py
agenta/client/backend/api_keys/client.py
agenta/client/backend/api_keys/raw_client.py
agenta/client/backend/applications/__init__.py
agenta/client/backend/applications/client.py
agenta/client/backend/applications/raw_client.py
agenta/client/backend/apps/__init__.py
agenta/client/backend/apps/client.py
agenta/client/backend/apps/raw_client.py
agenta/client/backend/auth/__init__.py
agenta/client/backend/auth/client.py
agenta/client/backend/auth/raw_client.py
agenta/client/backend/billing/__init__.py
agenta/client/backend/billing/client.py
agenta/client/backend/billing/raw_client.py
agenta/client/backend/client.py
agenta/client/backend/configs/__init__.py
agenta/client/backend/configs/client.py
agenta/client/backend/configs/raw_client.py
agenta/client/backend/containers/__init__.py
agenta/client/backend/containers/client.py
agenta/client/backend/containers/raw_client.py
agenta/client/backend/core/__init__.py
agenta/client/backend/core/api_error.py
agenta/client/backend/core/client_wrapper.py
agenta/client/backend/core/datetime_utils.py
agenta/client/backend/core/file.py
agenta/client/backend/core/force_multipart.py
agenta/client/backend/core/http_client.py
agenta/client/backend/core/http_response.py
agenta/client/backend/core/http_sse/__init__.py
agenta/client/backend/core/http_sse/_api.py
agenta/client/backend/core/http_sse/_decoders.py
agenta/client/backend/core/http_sse/_exceptions.py
agenta-0.81.2.dist-info/METADATA
agenta-0.81.2.dist-info/WHEEL
agenta-0.81.2.dist-info/RECORD
