Metadata-Version: 2.4
Name: agenta
Version: 0.81.2
Summary: The SDK for agenta is an open-source LLMOps platform.
Keywords: LLMOps,LLM,evaluation,prompt engineering
Author: Mahmoud Mabrouk
Author-email: mahmoud@agenta.ai
Requires-Python: >=3.11,<4.0
Classifier: Intended Audience :: Developers
Classifier: License :: OSI Approved :: MIT License
Classifier: Programming Language :: Python :: 3
Classifier: Programming Language :: Python :: 3.11
Classifier: Programming Language :: Python :: 3.12
Classifier: Programming Language :: Python :: 3.13
Classifier: Programming Language :: Python :: 3.14
Classifier: Programming Language :: Python :: 3.9
Classifier: Topic :: Software Development :: Libraries
Requires-Dist: daytona (>=0.136,<0.137)
Requires-Dist: fastapi (>=0.128)
Requires-Dist: httpx (>=0.28,<0.29)
Requires-Dist: jinja2 (>=3,<4)
Requires-Dist: litellm (>=1,<2)
Requires-Dist: openai (>=2,<3)
Requires-Dist: opentelemetry-api (>=1,<2)
Requires-Dist: opentelemetry-exporter-otlp-proto-http (>=1,<2)
Requires-Dist: opentelemetry-instrumentation (>=0.60b1,<0.61)
Requires-Dist: opentelemetry-sdk (>=1,<2)
Requires-Dist: orjson (>=3,<4)
Requires-Dist: pydantic (>=2,<3)
Requires-Dist: python-jsonpath (>=2,<3)
Requires-Dist: pyyaml (>=6,<7)
Requires-Dist: structlog (>=25,<26)
Project-URL: Documentation, https://agenta.ai/docs/
Project-URL: Homepage, https://agenta.ai
Project-URL: Repository, https://github.com/agenta-ai/agenta
